zero_sum_eval/__init__.py
zero_sum_eval/main.py
zero_sum_eval/analysis/__init__.py
zero_sum_eval/analysis/calculate_ratings.py
zero_sum_eval/core/__init__.py
zero_sum_eval/core/game_state.py
zero_sum_eval/core/player.py
zero_sum_eval/core/registry.py
zero_sum_eval/games/__init__.py
zero_sum_eval/games/chess/__init__.py
zero_sum_eval/games/chess/chess_dataset.py
zero_sum_eval/games/chess/chess_game.py
zero_sum_eval/games/chess/chess_player.py
zero_sum_eval/games/debate/__init__.py
zero_sum_eval/games/debate/debate_game.py
zero_sum_eval/games/debate/debate_judge.py
zero_sum_eval/games/debate/debate_player.py
zero_sum_eval/games/gandalf/__init__.py
zero_sum_eval/games/gandalf/gandalf_dataset.py
zero_sum_eval/games/gandalf/gandalf_game.py
zero_sum_eval/games/gandalf/gandalf_player.py
zero_sum_eval/games/liars_dice/__init__.py
zero_sum_eval/games/liars_dice/liars_dice_game.py
zero_sum_eval/games/liars_dice/liars_dice_player.py
zero_sum_eval/games/mathquiz/__init__.py
zero_sum_eval/games/mathquiz/mathquiz_dataset.py
zero_sum_eval/games/mathquiz/mathquiz_game.py
zero_sum_eval/games/mathquiz/mathquiz_player.py
zero_sum_eval/games/poker/__init__.py
zero_sum_eval/games/poker/poker_game.py
zero_sum_eval/games/poker/poker_player.py
zero_sum_eval/games/pyjail/__init__.py
zero_sum_eval/games/pyjail/pyjail_game.py
zero_sum_eval/games/pyjail/pyjail_player.py
zero_sum_eval/managers/__init__.py
zero_sum_eval/managers/game_manager.py
zero_sum_eval/managers/game_pool_manager.py
zero_sum_eval/managers/matchers/__init__.py
zero_sum_eval/managers/matchers/base.py
zero_sum_eval/managers/matchers/round_robin.py
zero_sum_eval/utils/__init__.py
zero_sum_eval/utils/checkpointing.py
zero_sum_eval/utils/config.py
zero_sum_eval/utils/logging.py
zero_sum_eval/utils/metrics.py
zero_sum_eval/utils/types.py
zero_sum_eval-0.3.0.dist-info/licenses/LICENSE
zero_sum_eval-0.3.0.dist-info/METADATA
zero_sum_eval-0.3.0.dist-info/WHEEL
zero_sum_eval-0.3.0.dist-info/entry_points.txt
zero_sum_eval-0.3.0.dist-info/top_level.txt
zero_sum_eval-0.3.0.dist-info/RECORD
