Metadata-Version: 2.4
Name: zero-sum-eval
Version: 0.3.0
Summary: A framework for evaluating LLMs using zero-sum multiplayer simulations
Author-email: Haidar Khan <haidark@gmail.com>, Hisham Alyahya <hisham.alyahya@outlook.com>, Yazeed Alnumay <yalnumay1@gmail.com>, M Saiful Bari <sbmaruf@gmail.com>
Project-URL: Homepage, https://github.com/facebookresearch/ZeroSumEval/
Project-URL: Bug Tracker, https://github.com/facebookresearch/ZeroSumEval/issues
Classifier: Programming Language :: Python :: 3
Classifier: License :: OSI Approved :: MIT License
Classifier: Operating System :: OS Independent
Classifier: Development Status :: 3 - Alpha
Classifier: Intended Audience :: Science/Research
Classifier: Topic :: Scientific/Engineering :: Artificial Intelligence
Requires-Python: >=3.9
License-File: LICENSE
Requires-Dist: dspy==2.5.41
Requires-Dist: pyyaml>=6.0
Requires-Dist: anthropic>=0.3.0
Requires-Dist: tabulate>=0.9.0
Requires-Dist: jsonlines>=3.1.0
Requires-Dist: docker>=6.0.0
Requires-Dist: random-word>=1.0.11
Requires-Dist: pathlib>=1.0
Requires-Dist: chess>=1.9.0
Requires-Dist: stockfish>=3.28.0
Requires-Dist: datasets>=2.12.0
Requires-Dist: scikit-learn>=1.0.0
Provides-Extra: dev
Requires-Dist: pytest>=7.0.0; extra == "dev"
Requires-Dist: pytest-cov>=4.0.0; extra == "dev"
Requires-Dist: pytest-runner>=6.0.0; extra == "dev"
Dynamic: license-file
